Metadata-Version: 2.1
Name: acdumo
Version: 1.1.2
Summary: Accelerated dual momentum
Home-page: https://github.com/anthony-aylward/acdumo
Author: Anthony Aylward, Serena Wu, Elijah Kun
Author-email: aaylward@eng.ucsd.edu
License: UNKNOWN
Platform: UNKNOWN
Classifier: Programming Language :: Python :: 3
Classifier: License :: OSI Approved :: MIT License
Classifier: Operating System :: OS Independent
Requires-Dist: email-validator
Requires-Dist: flask
Requires-Dist: flask-apscheduler
Requires-Dist: flask-login
Requires-Dist: flask-mail
Requires-Dist: flask-migrate
Requires-Dist: flask-misaka
Requires-Dist: flask-wtf
Requires-Dist: pyjwt
Requires-Dist: misaka
Requires-Dist: pandas
Requires-Dist: seaborn
Requires-Dist: wtforms
Requires-Dist: yahoofinancials
